AUTHORS
ChangeLog
INSTALL
LICENSE
MANIFEST.in
README.rst
TODO
setup.cfg
setup.py
keyutils/__init__.py
keyutils/_keyutils.c
keyutils/_keyutils.pyx
keyutils.egg-info/PKG-INFO
keyutils.egg-info/SOURCES.txt
keyutils.egg-info/dependency_links.txt
keyutils.egg-info/top_level.txt