Metadata-Version: 1.1
Name: keyutils
Version: 0.6
Summary: keyutils bindings for Python
Home-page: https://github.com/sassoftware/python-keyutils
Author: Mihai Ibanescu
Author-email: mihai.ibanescu@sas.com
License: Apache 2.0
Platform: Linux
Classifier: Topic :: Security
Classifier: Operating System :: POSIX :: Linux
Classifier: Programming Language :: Python :: 2.7
Classifier: Programming Language :: Python :: 3.3
Classifier: Programming Language :: Python :: 3.4
Classifier: Programming Language :: Python :: 3.5
Classifier: Programming Language :: Python :: 3.6
Classifier: Programming Language :: Python :: 3.7
